{
  "trading_date": "2026-07-19",
  "generated_at_utc": "2026-07-20T07:08:48.250499Z",
  "scope": "v4-email-driven-7sites",
  "group_total": {
    "net_sales_gbp": 15096.45,
    "checks": 932,
    "guests": 1009,
    "delivery_gbp": 4539.51,
    "in_store_gbp": 10556.94,
    "cash_gbp": 1130.54,
    "delivery_share_pct": 30.1,
    "cash_share_pct": 7.5
  },
  "sites": [
    {
      "code": "TT-BRIDEWELL",
      "aloha_report_name": "Taka Taka Bridewell",
      "net_sales_gbp": 2632.91,
      "checks": 188,
      "guests": 184,
      "avg_check_gbp": 14.0,
      "ppa_gbp": 14.31,
      "comps_gbp": 73.04,
      "promos_gbp": 8.6,
      "cash_gbp": 231.1,
      "revenue_centers": {
        "restaurant_gbp": 977.34,
        "kiosk_gbp": 337.94,
        "bar_gbp": 0.0,
        "deli_gbp": 0.0,
        "cc_gbp": 39.84,
        "deliveroo_gbp": 644.38,
        "ubereats_gbp": 633.41,
        "justeat_gbp": 0.0,
        "other_in_store_gbp": 0.0,
        "other_delivery_gbp": 0.0
      },
      "xlsx_rc_total_gbp": 2632.91,
      "rc_reconcile_diff_gbp": 0.0,
      "auto_captured_labels": [],
      "delivery_gbp": 1277.79,
      "in_store_gbp": 1355.12,
      "name": "Taka Taka Bridewell",
      "brand": "Taka Taka",
      "delivery_share_pct": 48.5,
      "cash_share_pct": 8.8,
      "below_target": false
    },
    {
      "code": "TT-BROADQUAY",
      "aloha_report_name": "Taka Taka Broadquay",
      "net_sales_gbp": 3278.06,
      "checks": 279,
      "guests": 272,
      "avg_check_gbp": 11.75,
      "ppa_gbp": 12.05,
      "comps_gbp": 48.44,
      "promos_gbp": 6.85,
      "cash_gbp": 190.9,
      "revenue_centers": {
        "restaurant_gbp": 2302.34,
        "kiosk_gbp": 0.0,
        "bar_gbp": 0.0,
        "deli_gbp": 0.0,
        "cc_gbp": 12.87,
        "deliveroo_gbp": 704.4,
        "ubereats_gbp": 239.99,
        "justeat_gbp": 18.46,
        "other_in_store_gbp": 0.0,
        "other_delivery_gbp": 0.0
      },
      "xlsx_rc_total_gbp": 3278.06,
      "rc_reconcile_diff_gbp": 0.0,
      "auto_captured_labels": [],
      "delivery_gbp": 962.85,
      "in_store_gbp": 2315.21,
      "name": "Taka Taka Broad Quay",
      "brand": "Taka Taka",
      "delivery_share_pct": 29.4,
      "cash_share_pct": 5.8,
      "below_target": false
    },
    {
      "code": "TT-MAGIC-ROLL",
      "aloha_report_name": "Taka Taka Magic Roll",
      "net_sales_gbp": 1978.0,
      "checks": 145,
      "guests": 142,
      "avg_check_gbp": 13.64,
      "ppa_gbp": 13.93,
      "comps_gbp": 85.72,
      "promos_gbp": 0.75,
      "cash_gbp": 196.1,
      "revenue_centers": {
        "restaurant_gbp": 1037.88,
        "kiosk_gbp": 131.49,
        "bar_gbp": 0.0,
        "deli_gbp": 0.0,
        "cc_gbp": 0.0,
        "deliveroo_gbp": 478.73,
        "ubereats_gbp": 306.98,
        "justeat_gbp": 22.92,
        "other_in_store_gbp": 0.0,
        "other_delivery_gbp": 0.0
      },
      "xlsx_rc_total_gbp": 1978.0,
      "rc_reconcile_diff_gbp": 0.0,
      "auto_captured_labels": [],
      "delivery_gbp": 808.63,
      "in_store_gbp": 1169.37,
      "name": "Taka Taka Magic Roll",
      "brand": "Taka Taka",
      "delivery_share_pct": 40.9,
      "cash_share_pct": 9.9,
      "below_target": false
    },
    {
      "code": "TT-JAMES-ST",
      "aloha_report_name": "Bath James Street",
      "net_sales_gbp": 1469.18,
      "checks": 128,
      "guests": 128,
      "avg_check_gbp": 11.48,
      "ppa_gbp": 11.48,
      "comps_gbp": 24.47,
      "promos_gbp": 7.85,
      "cash_gbp": 137.2,
      "revenue_centers": {
        "restaurant_gbp": 421.07,
        "kiosk_gbp": 652.03,
        "bar_gbp": 0.0,
        "deli_gbp": 0.0,
        "cc_gbp": 0.0,
        "deliveroo_gbp": 241.64,
        "ubereats_gbp": 122.49,
        "justeat_gbp": 31.95,
        "other_in_store_gbp": 0.0,
        "other_delivery_gbp": 0.0
      },
      "xlsx_rc_total_gbp": 1469.18,
      "rc_reconcile_diff_gbp": 0.0,
      "auto_captured_labels": [],
      "delivery_gbp": 396.08,
      "in_store_gbp": 1073.1,
      "name": "Taka Taka Bath James Street",
      "brand": "Taka Taka",
      "delivery_share_pct": 27.0,
      "cash_share_pct": 9.3,
      "below_target": true
    },
    {
      "code": "JARS-MEZE",
      "aloha_report_name": "Jars Meze",
      "net_sales_gbp": 1482.56,
      "checks": 24,
      "guests": 68,
      "avg_check_gbp": 61.77,
      "ppa_gbp": 21.8,
      "comps_gbp": 55.45,
      "promos_gbp": 0.0,
      "cash_gbp": 0,
      "revenue_centers": {
        "restaurant_gbp": 1482.56,
        "kiosk_gbp": 0.0,
        "bar_gbp": 0.0,
        "deli_gbp": 0.0,
        "cc_gbp": 0.0,
        "deliveroo_gbp": 0.0,
        "ubereats_gbp": 0.0,
        "justeat_gbp": 0.0,
        "other_in_store_gbp": 0.0,
        "other_delivery_gbp": 0.0
      },
      "xlsx_rc_total_gbp": 1482.56,
      "rc_reconcile_diff_gbp": 0.0,
      "auto_captured_labels": [],
      "delivery_gbp": 0.0,
      "in_store_gbp": 1482.56,
      "name": "Jars Meze",
      "brand": "Jars Meze",
      "delivery_share_pct": 0.0,
      "cash_share_pct": 0.0,
      "below_target": true
    },
    {
      "code": "TT-BOURNEMOUTH",
      "aloha_report_name": "Bournemouth",
      "net_sales_gbp": 1795.43,
      "checks": 124,
      "guests": 124,
      "avg_check_gbp": 14.48,
      "ppa_gbp": 14.48,
      "comps_gbp": 97.21,
      "promos_gbp": 1.55,
      "cash_gbp": 213.6,
      "revenue_centers": {
        "restaurant_gbp": 572.49,
        "kiosk_gbp": 128.78,
        "bar_gbp": 0.0,
        "deli_gbp": 0.0,
        "cc_gbp": 0.0,
        "deliveroo_gbp": 745.72,
        "ubereats_gbp": 277.7,
        "justeat_gbp": 70.74,
        "other_in_store_gbp": 0.0,
        "other_delivery_gbp": 0.0
      },
      "xlsx_rc_total_gbp": 1795.43,
      "rc_reconcile_diff_gbp": 0.0,
      "auto_captured_labels": [],
      "delivery_gbp": 1094.16,
      "in_store_gbp": 701.27,
      "name": "Taka Taka Bournemouth",
      "brand": "Taka Taka",
      "delivery_share_pct": 60.9,
      "cash_share_pct": 11.9,
      "below_target": true
    },
    {
      "code": "OPA-BATH",
      "aloha_report_name": "OPA Bath",
      "net_sales_gbp": 2460.31,
      "checks": 44,
      "guests": 91,
      "avg_check_gbp": 55.92,
      "ppa_gbp": 27.04,
      "comps_gbp": 63.31,
      "promos_gbp": 98.0,
      "cash_gbp": 161.64,
      "revenue_centers": {
        "restaurant_gbp": 2428.23,
        "kiosk_gbp": 0.0,
        "bar_gbp": 32.08,
        "deli_gbp": 0.0,
        "cc_gbp": 0.0,
        "deliveroo_gbp": 0.0,
        "ubereats_gbp": 0.0,
        "justeat_gbp": 0.0,
        "other_in_store_gbp": 0.0,
        "other_delivery_gbp": 0.0
      },
      "xlsx_rc_total_gbp": 2460.31,
      "rc_reconcile_diff_gbp": 0.0,
      "auto_captured_labels": [],
      "delivery_gbp": 0.0,
      "in_store_gbp": 2460.31,
      "name": "OPA Bath",
      "brand": "OPA",
      "delivery_share_pct": 0.0,
      "cash_share_pct": 6.6,
      "below_target": false
    }
  ],
  "marketman": {
    "section_status": "pending",
    "note": "Marketman procurement data pending \u2014 a scheduled email report needs to be set up in Marketman."
  },
  "labour": {
    "section_status": "pending",
    "note": "Labour cost % not included in the 'ALL METRICS' scheduled report. A second Labour-specific Aloha scheduled report is needed to surface labour on this dashboard."
  },
  "validation": {
    "status": "passed",
    "hard_failures": [],
    "warnings": [],
    "sites_below_target": [
      "TT-JAMES-ST",
      "JARS-MEZE",
      "TT-BOURNEMOUTH"
    ],
    "daily_target_gbp": 1800,
    "group_day_swing_pct": -18.6,
    "rules_evaluated": [
      "aloha_store_count_exact",
      "aloha_group_total_reconciles",
      "aloha_group_checks_reconciles",
      "aloha_group_guests_reconciles",
      "aloha_group_delivery_reconciles",
      "revenue_centers_sum_to_net",
      "parser_rc_reconciles_to_xlsx_total",
      "delivery_in_store_sum_to_net",
      "date_matches_yesterday",
      "no_negative_numbers",
      "site_revenue_sane",
      "avg_check_plausible",
      "site_below_target",
      "delivery_share_plausible",
      "group_day_swing"
    ]
  }
}