{
  "trading_date": "2026-05-28",
  "generated_at_utc": "2026-05-29T07:05:11.642404Z",
  "scope": "v4-email-driven-7sites",
  "group_total": {
    "net_sales_gbp": 18927.21,
    "checks": 1275,
    "guests": 1337,
    "delivery_gbp": 6242.21,
    "in_store_gbp": 12685.0,
    "cash_gbp": 726.96,
    "delivery_share_pct": 33.0,
    "cash_share_pct": 3.8
  },
  "sites": [
    {
      "code": "TT-BRIDEWELL",
      "aloha_report_name": "Taka Taka Bridewell",
      "net_sales_gbp": 3228.62,
      "checks": 231,
      "guests": 224,
      "avg_check_gbp": 13.98,
      "ppa_gbp": 14.41,
      "comps_gbp": 3.34,
      "promos_gbp": 13.3,
      "cash_gbp": 89.7,
      "revenue_centers": {
        "restaurant_gbp": 715.21,
        "kiosk_gbp": 493.02,
        "bar_gbp": 0.0,
        "deli_gbp": 0.0,
        "cc_gbp": 11.08,
        "deliveroo_gbp": 1305.81,
        "ubereats_gbp": 686.46,
        "justeat_gbp": 17.04,
        "other_in_store_gbp": 0.0,
        "other_delivery_gbp": 0.0
      },
      "xlsx_rc_total_gbp": 3228.62,
      "rc_reconcile_diff_gbp": 0.0,
      "auto_captured_labels": [],
      "delivery_gbp": 2009.31,
      "in_store_gbp": 1219.31,
      "name": "Taka Taka Bridewell",
      "brand": "Taka Taka",
      "delivery_share_pct": 62.2,
      "cash_share_pct": 2.8,
      "below_target": false
    },
    {
      "code": "TT-BROADQUAY",
      "aloha_report_name": "Taka Taka Broadquay",
      "net_sales_gbp": 3291.06,
      "checks": 311,
      "guests": 309,
      "avg_check_gbp": 10.58,
      "ppa_gbp": 10.65,
      "comps_gbp": 68.09,
      "promos_gbp": 7.55,
      "cash_gbp": 49.55,
      "revenue_centers": {
        "restaurant_gbp": 2520.23,
        "kiosk_gbp": 0.0,
        "bar_gbp": 0.0,
        "deli_gbp": 0.0,
        "cc_gbp": 0.0,
        "deliveroo_gbp": 453.76,
        "ubereats_gbp": 312.49,
        "justeat_gbp": 4.58,
        "other_in_store_gbp": 0.0,
        "other_delivery_gbp": 0.0
      },
      "xlsx_rc_total_gbp": 3291.06,
      "rc_reconcile_diff_gbp": 0.0,
      "auto_captured_labels": [],
      "delivery_gbp": 770.83,
      "in_store_gbp": 2520.23,
      "name": "Taka Taka Broad Quay",
      "brand": "Taka Taka",
      "delivery_share_pct": 23.4,
      "cash_share_pct": 1.5,
      "below_target": false
    },
    {
      "code": "TT-MAGIC-ROLL",
      "aloha_report_name": "Taka Taka Magic Roll",
      "net_sales_gbp": 2634.36,
      "checks": 233,
      "guests": 222,
      "avg_check_gbp": 11.31,
      "ppa_gbp": 11.87,
      "comps_gbp": 10.62,
      "promos_gbp": 20.45,
      "cash_gbp": 195.55,
      "revenue_centers": {
        "restaurant_gbp": 889.48,
        "kiosk_gbp": 472.3,
        "bar_gbp": 0.0,
        "deli_gbp": 0.0,
        "cc_gbp": 32.75,
        "deliveroo_gbp": 657.24,
        "ubereats_gbp": 540.34,
        "justeat_gbp": 42.25,
        "other_in_store_gbp": 0.0,
        "other_delivery_gbp": 0.0
      },
      "xlsx_rc_total_gbp": 2634.36,
      "rc_reconcile_diff_gbp": 0.0,
      "auto_captured_labels": [],
      "delivery_gbp": 1239.83,
      "in_store_gbp": 1394.53,
      "name": "Taka Taka Magic Roll",
      "brand": "Taka Taka",
      "delivery_share_pct": 47.1,
      "cash_share_pct": 7.4,
      "below_target": false
    },
    {
      "code": "TT-JAMES-ST",
      "aloha_report_name": "Bath James Street",
      "net_sales_gbp": 2672.36,
      "checks": 267,
      "guests": 255,
      "avg_check_gbp": 10.01,
      "ppa_gbp": 10.48,
      "comps_gbp": 25.99,
      "promos_gbp": 16.05,
      "cash_gbp": 104.85,
      "revenue_centers": {
        "restaurant_gbp": 575.68,
        "kiosk_gbp": 1301.26,
        "bar_gbp": 0.0,
        "deli_gbp": 0.0,
        "cc_gbp": 68.75,
        "deliveroo_gbp": 378.37,
        "ubereats_gbp": 296.14,
        "justeat_gbp": 52.16,
        "other_in_store_gbp": 0.0,
        "other_delivery_gbp": 0.0
      },
      "xlsx_rc_total_gbp": 2672.36,
      "rc_reconcile_diff_gbp": 0.0,
      "auto_captured_labels": [],
      "delivery_gbp": 726.67,
      "in_store_gbp": 1945.69,
      "name": "Taka Taka Bath James Street",
      "brand": "Taka Taka",
      "delivery_share_pct": 27.2,
      "cash_share_pct": 3.9,
      "below_target": false
    },
    {
      "code": "JARS-MEZE",
      "aloha_report_name": "Jars Meze",
      "net_sales_gbp": 3119.22,
      "checks": 60,
      "guests": 127,
      "avg_check_gbp": 51.99,
      "ppa_gbp": 24.56,
      "comps_gbp": 145.2,
      "promos_gbp": 0.0,
      "cash_gbp": 0,
      "revenue_centers": {
        "restaurant_gbp": 3119.22,
        "kiosk_gbp": 0.0,
        "bar_gbp": 0.0,
        "deli_gbp": 0.0,
        "cc_gbp": 0.0,
        "deliveroo_gbp": 0.0,
        "ubereats_gbp": 0.0,
        "justeat_gbp": 0.0,
        "other_in_store_gbp": 0.0,
        "other_delivery_gbp": 0.0
      },
      "xlsx_rc_total_gbp": 3119.22,
      "rc_reconcile_diff_gbp": 0.0,
      "auto_captured_labels": [],
      "delivery_gbp": 0.0,
      "in_store_gbp": 3119.22,
      "name": "Jars Meze",
      "brand": "Jars Meze",
      "delivery_share_pct": 0.0,
      "cash_share_pct": 0.0,
      "below_target": false
    },
    {
      "code": "TT-BOURNEMOUTH",
      "aloha_report_name": "Bournemouth",
      "net_sales_gbp": 2188.89,
      "checks": 144,
      "guests": 140,
      "avg_check_gbp": 15.2,
      "ppa_gbp": 15.63,
      "comps_gbp": 0.0,
      "promos_gbp": 15.6,
      "cash_gbp": 256.05,
      "revenue_centers": {
        "restaurant_gbp": 556.13,
        "kiosk_gbp": 137.19,
        "bar_gbp": 0.0,
        "deli_gbp": 0.0,
        "cc_gbp": 0.0,
        "deliveroo_gbp": 1100.17,
        "ubereats_gbp": 299.49,
        "justeat_gbp": 95.91,
        "other_in_store_gbp": 0.0,
        "other_delivery_gbp": 0.0
      },
      "xlsx_rc_total_gbp": 2188.89,
      "rc_reconcile_diff_gbp": 0.0,
      "auto_captured_labels": [],
      "delivery_gbp": 1495.57,
      "in_store_gbp": 693.32,
      "name": "Taka Taka Bournemouth",
      "brand": "Taka Taka",
      "delivery_share_pct": 68.3,
      "cash_share_pct": 11.7,
      "below_target": false
    },
    {
      "code": "OPA-BATH",
      "aloha_report_name": "OPA Bath",
      "net_sales_gbp": 1792.7,
      "checks": 29,
      "guests": 60,
      "avg_check_gbp": 61.82,
      "ppa_gbp": 29.88,
      "comps_gbp": 7.64,
      "promos_gbp": 35.0,
      "cash_gbp": 31.26,
      "revenue_centers": {
        "restaurant_gbp": 1792.7,
        "kiosk_gbp": 0.0,
        "bar_gbp": 0.0,
        "deli_gbp": 0.0,
        "cc_gbp": 0.0,
        "deliveroo_gbp": 0.0,
        "ubereats_gbp": 0.0,
        "justeat_gbp": 0.0,
        "other_in_store_gbp": 0.0,
        "other_delivery_gbp": 0.0
      },
      "xlsx_rc_total_gbp": 1792.7,
      "rc_reconcile_diff_gbp": 0.0,
      "auto_captured_labels": [],
      "delivery_gbp": 0.0,
      "in_store_gbp": 1792.7,
      "name": "OPA Bath",
      "brand": "OPA",
      "delivery_share_pct": 0.0,
      "cash_share_pct": 1.7,
      "below_target": true
    }
  ],
  "marketman": {
    "section_status": "pending",
    "note": "Marketman procurement data pending \u2014 a scheduled email report needs to be set up in Marketman."
  },
  "labour": {
    "section_status": "pending",
    "note": "Labour cost % not included in the 'ALL METRICS' scheduled report. A second Labour-specific Aloha scheduled report is needed to surface labour on this dashboard."
  },
  "validation": {
    "status": "passed",
    "hard_failures": [],
    "warnings": [],
    "sites_below_target": [
      "OPA-BATH"
    ],
    "daily_target_gbp": 1800,
    "group_day_swing_pct": 9.4,
    "rules_evaluated": [
      "aloha_store_count_exact",
      "aloha_group_total_reconciles",
      "aloha_group_checks_reconciles",
      "aloha_group_guests_reconciles",
      "aloha_group_delivery_reconciles",
      "revenue_centers_sum_to_net",
      "parser_rc_reconciles_to_xlsx_total",
      "delivery_in_store_sum_to_net",
      "date_matches_yesterday",
      "no_negative_numbers",
      "site_revenue_sane",
      "avg_check_plausible",
      "site_below_target",
      "delivery_share_plausible",
      "group_day_swing"
    ]
  }
}