{
  "trading_date": "2026-05-11",
  "generated_at_utc": "2026-05-12T08:55:39.512375Z",
  "scope": "v4-email-driven-7sites",
  "group_total": {
    "net_sales_gbp": 9878.7,
    "checks": 760,
    "guests": 761,
    "delivery_gbp": 4541.23,
    "in_store_gbp": 5337.47,
    "cash_gbp": 331.6,
    "delivery_share_pct": 46.0,
    "cash_share_pct": 3.4
  },
  "sites": [
    {
      "code": "TT-BRIDEWELL",
      "aloha_report_name": "Taka Taka Bridewell",
      "net_sales_gbp": 2637.38,
      "checks": 207,
      "guests": 200,
      "avg_check_gbp": 12.74,
      "ppa_gbp": 13.19,
      "comps_gbp": 102.8,
      "promos_gbp": 11.85,
      "cash_gbp": 38.8,
      "revenue_centers": {
        "restaurant_gbp": 643.9,
        "kiosk_gbp": 401.02,
        "bar_gbp": 0.0,
        "deli_gbp": 0.0,
        "cc_gbp": 12.04,
        "deliveroo_gbp": 860.86,
        "ubereats_gbp": 702.56,
        "justeat_gbp": 17.0,
        "other_in_store_gbp": 0.0,
        "other_delivery_gbp": 0.0
      },
      "xlsx_rc_total_gbp": 2637.38,
      "rc_reconcile_diff_gbp": 0.0,
      "auto_captured_labels": [],
      "delivery_gbp": 1580.42,
      "in_store_gbp": 1056.96,
      "name": "Taka Taka Bridewell",
      "brand": "Taka Taka",
      "delivery_share_pct": 59.9,
      "cash_share_pct": 1.5,
      "below_target": false
    },
    {
      "code": "TT-BROADQUAY",
      "aloha_report_name": "Taka Taka Broadquay",
      "net_sales_gbp": 1738.69,
      "checks": 171,
      "guests": 168,
      "avg_check_gbp": 10.17,
      "ppa_gbp": 10.35,
      "comps_gbp": 25.46,
      "promos_gbp": 1.35,
      "cash_gbp": 113.5,
      "revenue_centers": {
        "restaurant_gbp": 1058.03,
        "kiosk_gbp": 0.0,
        "bar_gbp": 0.0,
        "deli_gbp": 0.0,
        "cc_gbp": 28.95,
        "deliveroo_gbp": 486.22,
        "ubereats_gbp": 165.49,
        "justeat_gbp": 0.0,
        "other_in_store_gbp": 0.0,
        "other_delivery_gbp": 0.0
      },
      "xlsx_rc_total_gbp": 1738.69,
      "rc_reconcile_diff_gbp": 0.0,
      "auto_captured_labels": [],
      "delivery_gbp": 651.71,
      "in_store_gbp": 1086.98,
      "name": "Taka Taka Broad Quay",
      "brand": "Taka Taka",
      "delivery_share_pct": 37.5,
      "cash_share_pct": 6.5,
      "below_target": true
    },
    {
      "code": "TT-MAGIC-ROLL",
      "aloha_report_name": "Taka Taka Magic Roll",
      "net_sales_gbp": 1779.62,
      "checks": 160,
      "guests": 152,
      "avg_check_gbp": 11.12,
      "ppa_gbp": 11.71,
      "comps_gbp": 66.27,
      "promos_gbp": 8.75,
      "cash_gbp": 64.2,
      "revenue_centers": {
        "restaurant_gbp": 644.0,
        "kiosk_gbp": 271.2,
        "bar_gbp": 0.0,
        "deli_gbp": 0.0,
        "cc_gbp": 0.0,
        "deliveroo_gbp": 414.51,
        "ubereats_gbp": 435.41,
        "justeat_gbp": 14.5,
        "other_in_store_gbp": 0.0,
        "other_delivery_gbp": 0.0
      },
      "xlsx_rc_total_gbp": 1779.62,
      "rc_reconcile_diff_gbp": 0.0,
      "auto_captured_labels": [],
      "delivery_gbp": 864.42,
      "in_store_gbp": 915.2,
      "name": "Taka Taka Magic Roll",
      "brand": "Taka Taka",
      "delivery_share_pct": 48.6,
      "cash_share_pct": 3.6,
      "below_target": true
    },
    {
      "code": "TT-JAMES-ST",
      "aloha_report_name": "Bath James Street",
      "net_sales_gbp": 1250.74,
      "checks": 117,
      "guests": 116,
      "avg_check_gbp": 10.69,
      "ppa_gbp": 10.78,
      "comps_gbp": 49.59,
      "promos_gbp": 5.0,
      "cash_gbp": 41.05,
      "revenue_centers": {
        "restaurant_gbp": 248.89,
        "kiosk_gbp": 446.78,
        "bar_gbp": 0.0,
        "deli_gbp": 0.0,
        "cc_gbp": 1.83,
        "deliveroo_gbp": 336.83,
        "ubereats_gbp": 138.54,
        "justeat_gbp": 77.87,
        "other_in_store_gbp": 0.0,
        "other_delivery_gbp": 0.0
      },
      "xlsx_rc_total_gbp": 1250.74,
      "rc_reconcile_diff_gbp": 0.0,
      "auto_captured_labels": [],
      "delivery_gbp": 553.24,
      "in_store_gbp": 697.5,
      "name": "Taka Taka Bath James Street",
      "brand": "Taka Taka",
      "delivery_share_pct": 44.2,
      "cash_share_pct": 3.3,
      "below_target": true
    },
    {
      "code": "JARS-MEZE",
      "aloha_report_name": "Jars Meze",
      "net_sales_gbp": 199.59,
      "checks": 6,
      "guests": 11,
      "avg_check_gbp": 33.27,
      "ppa_gbp": 18.14,
      "comps_gbp": 0.0,
      "promos_gbp": 0.0,
      "cash_gbp": 0,
      "revenue_centers": {
        "restaurant_gbp": 199.59,
        "kiosk_gbp": 0.0,
        "bar_gbp": 0.0,
        "deli_gbp": 0.0,
        "cc_gbp": 0.0,
        "deliveroo_gbp": 0.0,
        "ubereats_gbp": 0.0,
        "justeat_gbp": 0.0,
        "other_in_store_gbp": 0.0,
        "other_delivery_gbp": 0.0
      },
      "xlsx_rc_total_gbp": 199.59,
      "rc_reconcile_diff_gbp": 0.0,
      "auto_captured_labels": [],
      "delivery_gbp": 0.0,
      "in_store_gbp": 199.59,
      "name": "Jars Meze",
      "brand": "Jars Meze",
      "delivery_share_pct": 0.0,
      "cash_share_pct": 0.0,
      "below_target": true
    },
    {
      "code": "TT-BOURNEMOUTH",
      "aloha_report_name": "Bournemouth",
      "net_sales_gbp": 1253.87,
      "checks": 83,
      "guests": 82,
      "avg_check_gbp": 15.11,
      "ppa_gbp": 15.29,
      "comps_gbp": 79.01,
      "promos_gbp": 0.65,
      "cash_gbp": 67.05,
      "revenue_centers": {
        "restaurant_gbp": 298.05,
        "kiosk_gbp": 81.25,
        "bar_gbp": 0.0,
        "deli_gbp": 0.0,
        "cc_gbp": 0.0,
        "deliveroo_gbp": 577.63,
        "ubereats_gbp": 226.94,
        "justeat_gbp": 70.0,
        "other_in_store_gbp": 0.0,
        "other_delivery_gbp": 0.0
      },
      "xlsx_rc_total_gbp": 1253.87,
      "rc_reconcile_diff_gbp": 0.0,
      "auto_captured_labels": [],
      "delivery_gbp": 874.57,
      "in_store_gbp": 379.3,
      "name": "Taka Taka Bournemouth",
      "brand": "Taka Taka",
      "delivery_share_pct": 69.7,
      "cash_share_pct": 5.3,
      "below_target": true
    },
    {
      "code": "OPA-BATH",
      "aloha_report_name": "OPA Bath",
      "net_sales_gbp": 1018.81,
      "checks": 16,
      "guests": 32,
      "avg_check_gbp": 63.68,
      "ppa_gbp": 31.84,
      "comps_gbp": 3.0,
      "promos_gbp": 17.9,
      "cash_gbp": 7.0,
      "revenue_centers": {
        "restaurant_gbp": 1001.94,
        "kiosk_gbp": 0.0,
        "bar_gbp": 0.0,
        "deli_gbp": 0.0,
        "cc_gbp": 0.0,
        "deliveroo_gbp": 16.87,
        "ubereats_gbp": 0.0,
        "justeat_gbp": 0.0,
        "other_in_store_gbp": 0.0,
        "other_delivery_gbp": 0.0
      },
      "xlsx_rc_total_gbp": 1018.81,
      "rc_reconcile_diff_gbp": 0.0,
      "auto_captured_labels": [],
      "delivery_gbp": 16.87,
      "in_store_gbp": 1001.94,
      "name": "OPA Bath",
      "brand": "OPA",
      "delivery_share_pct": 1.7,
      "cash_share_pct": 0.7,
      "below_target": true
    }
  ],
  "marketman": {
    "section_status": "pending",
    "note": "Marketman procurement data pending \u2014 a scheduled email report needs to be set up in Marketman."
  },
  "labour": {
    "section_status": "pending",
    "note": "Labour cost % not included in the 'ALL METRICS' scheduled report. A second Labour-specific Aloha scheduled report is needed to surface labour on this dashboard."
  },
  "validation": {
    "status": "passed",
    "hard_failures": [],
    "warnings": [],
    "sites_below_target": [
      "TT-BROADQUAY",
      "TT-MAGIC-ROLL",
      "TT-JAMES-ST",
      "JARS-MEZE",
      "TT-BOURNEMOUTH",
      "OPA-BATH"
    ],
    "daily_target_gbp": 1800,
    "group_day_swing_pct": -27.9,
    "rules_evaluated": [
      "aloha_store_count_exact",
      "aloha_group_total_reconciles",
      "aloha_group_checks_reconciles",
      "aloha_group_guests_reconciles",
      "aloha_group_delivery_reconciles",
      "revenue_centers_sum_to_net",
      "parser_rc_reconciles_to_xlsx_total",
      "delivery_in_store_sum_to_net",
      "date_matches_yesterday",
      "no_negative_numbers",
      "site_revenue_sane",
      "avg_check_plausible",
      "site_below_target",
      "delivery_share_plausible",
      "group_day_swing"
    ]
  }
}